omikuji_fast/__init__.py
omikuji_fast/_libomikuji_fast.py
omikuji_fast/_libomikuji_fast__ffi.py
omikuji_fast/_libomikuji_fast__lib.so
omikuji_fast-0.3.0.dist-info/LICENSE
omikuji_fast-0.3.0.dist-info/METADATA
omikuji_fast-0.3.0.dist-info/WHEEL
omikuji_fast-0.3.0.dist-info/top_level.txt
omikuji_fast-0.3.0.dist-info/RECORD
