Metadata-Version: 2.1
Name: omikuji_fast
Version: 0.3.0
Summary: Python binding to Omikuji, an efficient implementation of Partioned Label Trees and its variations for extreme multi-label classification
Home-page: https://github.com/tomtung/omikuji_fast
Author: Avik Pal
Author-email: avik.pal.2017@gmail.com
License: MIT
Platform: any
Classifier: Programming Language :: Python :: 3
Classifier: Programming Language :: Python :: 3.6
Classifier: Programming Language :: Python :: 3.7
Classifier: Programming Language :: Python :: Implementation :: CPython
Classifier: Programming Language :: Rust
Classifier: License :: OSI Approved :: MIT License
Classifier: Operating System :: OS Independent
Classifier: Intended Audience :: Developers
Classifier: Intended Audience :: Science/Research
Classifier: Topic :: Scientific/Engineering :: Artificial Intelligence
Classifier: Topic :: Software Development :: Libraries
Requires-Python: >=3.5
